ie_mbdbl2017_C_yahoo_ks_datareader
