Metadata-Version: 1.0
Name: ie-mbdbl2017-C-yahoo-ks-datareader
Version: 1.0.4
Summary: Python Packaging for Risk and Fraud Course, GMBD2017, GroupC
Home-page: https://github.com/dancual/pythonpackagesample
Author: Daniel Serrano
Author-email: dserrano1983@gmail.com
License: MIT
Platform: UNKNOWN
